aislib/__init__.py
aislib/data_load.py
aislib/misc_utils.py
aislib/plink_utils.py
aislib/pytorch_modules.py
aislib/pytorch_utils.py
aislib-0.5.0.dist-info/WHEEL
aislib-0.5.0.dist-info/METADATA
aislib-0.5.0.dist-info/RECORD
