Metadata-Version: 2.3
Name: aislib
Version: 0.5.0
Summary: 
Author: Arnor Sigurdsson
Requires-Dist: tqdm>=4.66.4
Requires-Dist: termcolor>=3.1.0
Requires-Dist: pandas>=2.2.2 ; extra == 'full'
Requires-Dist: numpy>=2.0.1 ; extra == 'full'
Requires-Dist: torch>=2.4.0 ; extra == 'full'
Requires-Dist: torchvision>=0.18.0 ; extra == 'full'
Requires-Dist: py>=1.11.0 ; extra == 'full'
Requires-Dist: matplotlib>=3.9.1 ; extra == 'full'
Requires-Dist: scikit-learn>=1.5.1 ; extra == 'full'
Requires-Dist: seaborn>=0.13.0 ; extra == 'full'
Requires-Dist: sympy>=1.13.1 ; extra == 'full'
Requires-Python: >=3.12
Provides-Extra: full
